demo/__init__.py
demo/ioc_test.py
demo/test.py
demo/test_server.py
demo/test_simple_server.py
eleme.openapi.python.sdk-1.8.0.dist-info/DESCRIPTION.rst
eleme.openapi.python.sdk-1.8.0.dist-info/METADATA
eleme.openapi.python.sdk-1.8.0.dist-info/RECORD
eleme.openapi.python.sdk-1.8.0.dist-info/WHEEL
eleme.openapi.python.sdk-1.8.0.dist-info/metadata.json
eleme.openapi.python.sdk-1.8.0.dist-info/top_level.txt
generatetool/__init__.py
generatetool/generate_tool.py
sdk/__init__.py
sdk/config.py
sdk/sdk_logging.py
sdk/apis/__init__.py
sdk/apis/activity_service.py
sdk/apis/finance_service.py
sdk/apis/message_service.py
sdk/apis/order_service.py
sdk/apis/packs_service.py
sdk/apis/product_service.py
sdk/apis/shop_service.py
sdk/apis/ugc_service.py
sdk/apis/user_service.py
sdk/exception/__init__.py
sdk/exception/access_denied_exception.py
sdk/exception/business_exception.py
sdk/exception/exceed_limit_exception.py
sdk/exception/illegal_request_exception.py
sdk/exception/invalid_signature_exception.py
sdk/exception/invalid_timestamp_exception.py
sdk/exception/method_not_allowed_exception.py
sdk/exception/permission_denied_exception.py
sdk/exception/service_exception.py
sdk/exception/system_exception.py
sdk/exception/unauthorized_exception.py
sdk/exception/validation_failed_exception.py
sdk/oauth/__init__.py
sdk/oauth/oauth_client.py
sdk/protocol/__init__.py
sdk/protocol/rpc_client.py
sdk/util/__init__.py
sdk/util/callback_signature_util.py
server/__init__.py
server/global_config.py
server/server_handle.py
server/start_up.py
