Metadata-Version: 2.0
Name: eleme.openapi.python.sdk
Version: 1.8.0
Summary: eleme openapi python sdk
Home-page: UNKNOWN
Author: David
Author-email: open.shop@ele.me
License: MIT License
Keywords: eleme,openapi
Platform: UNKNOWN
